mrputils/__init__.py
mrputils/loaders.py
mrputils/processors.py
mrputils-0.7.2.dist-info/LICENSE
mrputils-0.7.2.dist-info/METADATA
mrputils-0.7.2.dist-info/WHEEL
mrputils-0.7.2.dist-info/top_level.txt
mrputils-0.7.2.dist-info/RECORD
