Metadata-Version: 2.1
Name: mrputils
Version: 0.7.2
Summary: This is a util module to help with movie revenue prediction
Home-page: https://github.com/scienclick/pde_cap_mrp_zagros/tree/main/mrputils
Author: Amir Shamsa
Author-email: amirshamsa@gmail.com
License: Apache License 2.0
Platform: UNKNOWN
Requires-Dist: numpy
Requires-Dist: pandas
Requires-Dist: scikit-learn
Requires-Dist: nltk
